datamart_isi/__init__.py
datamart_isi/augment.py
datamart_isi/config.py
datamart_isi/config_services.py
datamart_isi/datamart-services.json
datamart_isi/entries.py
datamart_isi/entries_old.py
datamart_isi/profiler.py
datamart_isi/rest.py
datamart_isi/cache/__init__.py
datamart_isi/cache/general_search_cache.py
datamart_isi/cache/materializer_cache.py
datamart_isi/cache/metadata_cache.py
datamart_isi/cache/wikidata_cache.py
datamart_isi/joiners/__init__.py
datamart_isi/joiners/exact_match_joiner.py
datamart_isi/joiners/join_result.py
datamart_isi/joiners/joiner_base.py
datamart_isi/joiners/rltk_joiner.py
datamart_isi/joiners/join_feature/__init__.py
datamart_isi/joiners/join_feature/feature_base.py
datamart_isi/joiners/join_feature/feature_classes.py
datamart_isi/joiners/join_feature/feature_factory.py
datamart_isi/joiners/join_feature/feature_pairs.py
datamart_isi/joiners/join_feature/wrapped_similarity_functions.py
datamart_isi/materializers/__init__.py
datamart_isi/materializers/general_materializer.py
datamart_isi/materializers/materializer_base.py
datamart_isi/materializers/wikitables_materializer.py
datamart_isi/materializers/parsers/__init__.py
datamart_isi/materializers/parsers/csv_parser.py
datamart_isi/materializers/parsers/excel_parser.py
datamart_isi/materializers/parsers/html_parser.py
datamart_isi/materializers/parsers/json_parser.py
datamart_isi/materializers/parsers/parse_result.py
datamart_isi/materializers/parsers/parser_base.py
datamart_isi/metadata/__init__.py
datamart_isi/metadata/global_metadata.py
datamart_isi/metadata/metadata_base.py
datamart_isi/metadata/variable_metadata.py
datamart_isi/profilers/__init__.py
datamart_isi/profilers/basic_profiler.py
datamart_isi/profilers/dsbox_profiler.py
datamart_isi/profilers/two_ravens_profiler.py
datamart_isi/profilers/helpers/__init__.py
datamart_isi/profilers/helpers/feature_compute_hih.py
datamart_isi/profilers/helpers/feature_compute_lfh.py
datamart_isi/utilities/__init__.py
datamart_isi-2.1.10.dist-info/LICENSE
datamart_isi-2.1.10.dist-info/METADATA
datamart_isi-2.1.10.dist-info/WHEEL
datamart_isi-2.1.10.dist-info/top_level.txt
datamart_isi-2.1.10.dist-info/RECORD
